scircm/__init__.py
scircm/__main__.py
scircm/base.py
scircm/old_vis.py
scircm/randm.py
scircm/rcm_noprot.py
scircm/stats.py
scircm/vae.py
scircm/vis.py
sircle/__init__.py
sircle/base.py
sircle-0.0.5.data/data/LICENSE
sircle-0.0.5.dist-info/LICENSE
sircle-0.0.5.dist-info/METADATA
sircle-0.0.5.dist-info/WHEEL
sircle-0.0.5.dist-info/entry_points.txt
sircle-0.0.5.dist-info/top_level.txt
sircle-0.0.5.dist-info/RECORD
